Workbook

Sheet Summary
A1: Invoice Extractor — Summary
A3: Invoices processed | B3: =COUNTA(Invoices!B2:B)
A4: OK | B4: =COUNTIF(Invoices!C2:C,"OK")
A5: Needs review | B5: =COUNTIF(Invoices!C2:C,"Needs review")
A6: Extraction failed | B6: =COUNTIF(Invoices!C2:C,"Extraction failed")
A9: Spend by category (USD lines)
A10: Category | B10: Amount | C10: Lines
A11: Software & Subscriptions | B11: =SUMIFS('Line Items'!I2:I,'Line Items'!F2:F,A11,'Line Items'!J2:J,"USD") | C11: =COUNTIF('Line Items'!F2:F,A11)
A12: Office Supplies | B12: =SUMIFS('Line Items'!I2:I,'Line Items'!F2:F,A12,'Line Items'!J2:J,"USD") | C12: =COUNTIF('Line Items'!F2:F,A12)
A13: Equipment | B13: =SUMIFS('Line Items'!I2:I,'Line Items'!F2:F,A13,'Line Items'!J2:J,"USD") | C13: =COUNTIF('Line Items'!F2:F,A13)
A14: Travel | B14: =SUMIFS('Line Items'!I2:I,'Line Items'!F2:F,A14,'Line Items'!J2:J,"USD") | C14: =COUNTIF('Line Items'!F2:F,A14)
A15: Meals & Entertainment | B15: =SUMIFS('Line Items'!I2:I,'Line Items'!F2:F,A15,'Line Items'!J2:J,"USD") | C15: =COUNTIF('Line Items'!F2:F,A15)
A16: Advertising & Marketing | B16: =SUMIFS('Line Items'!I2:I,'Line Items'!F2:F,A16,'Line Items'!J2:J,"USD") | C16: =COUNTIF('Line Items'!F2:F,A16)
A17: Professional Services | B17: =SUMIFS('Line Items'!I2:I,'Line Items'!F2:F,A17,'Line Items'!J2:J,"USD") | C17: =COUNTIF('Line Items'!F2:F,A17)
A18: Shipping & Logistics | B18: =SUMIFS('Line Items'!I2:I,'Line Items'!F2:F,A18,'Line Items'!J2:J,"USD") | C18: =COUNTIF('Line Items'!F2:F,A18)
A19: Rent & Utilities | B19: =SUMIFS('Line Items'!I2:I,'Line Items'!F2:F,A19,'Line Items'!J2:J,"USD") | C19: =COUNTIF('Line Items'!F2:F,A19)
A20: Other | B20: =SUMIFS('Line Items'!I2:I,'Line Items'!F2:F,A20,'Line Items'!J2:J,"USD") | C20: =COUNTIF('Line Items'!F2:F,A20)

Sheet Invoices
A1: processed_at_utc | B1: file | C1: status | D1: issues | E1: vendor | F1: invoice_number | G1: invoice_date | H1: due_date | I1: currency | J1: subtotal | K1: tax_rate | L1: tax | M1: total | N1: line_items_sum | O1: line_item_count | P1: bill_to | Q1: vendor_address

Sheet Line Items
A1: invoice_number | B1: vendor | C1: invoice_date | D1: line | E1: description | F1: category | G1: quantity | H1: unit_price | I1: amount | J1: currency
